pyvulnerabilitylookup/__init__.py
pyvulnerabilitylookup/api.py
pyvulnerabilitylookup/py.typed
pyvulnerabilitylookup-2.19.0.dist-info/METADATA
pyvulnerabilitylookup-2.19.0.dist-info/WHEEL
pyvulnerabilitylookup-2.19.0.dist-info/entry_points.txt
pyvulnerabilitylookup-2.19.0.dist-info/licenses/LICENSE
pyvulnerabilitylookup-2.19.0.dist-info/RECORD
